[
  {
    "github": [
      {
        "username": "LoveDoLove",
        "projects": [
          "EasyKit",
          "cloudflare-smart-tools",
          "alist-freebsd",
          "memos-freebsd",
          "panindex-freebsd",
          "cloudreve-freebsd",
          "Github-Profile-Manager",
          "Github-Forks-Sync-Manager",
          "Github-Action-Cleaner",
          "CS_CommonUtilities",
          "TpLinkFirmwareDirectory"
        ]
      }
    ],
    "gitlab": [],
    "gitee": [],
    "bitbucket": []
  }
]
